project_patcher/cli.py
project_patcher/lazy.py
project_patcher/singleton.py
project_patcher/utils.py
project_patcher/metadata/base.py
project_patcher/metadata/file.py
project_patcher/metadata/files/gitrepo.py
project_patcher/metadata/files/osf.py
project_patcher/metadata/files/url.py
project_patcher/struct/codec.py
project_patcher/struct/registry.py
project_patcher/workspace/patcher.py
project_patcher/workspace/project.py
project_patcher-0.3.0.dist-info/LICENSE
project_patcher-0.3.0.dist-info/METADATA
project_patcher-0.3.0.dist-info/WHEEL
project_patcher-0.3.0.dist-info/entry_points.txt
project_patcher-0.3.0.dist-info/top_level.txt
project_patcher-0.3.0.dist-info/RECORD
