Metadata-Version: 2.1
Name: project-patcher
Version: 0.3.0
Summary: A project constructor, diff generator, and patcher rolled into one
Author-email: Aaron Haim <ahaim@ashwork.net>
License: MIT License
Project-URL: homepage, https://github.com/ahaim5357/project-patcher
Project-URL: issue_tracker, https://github.com/ahaim5357/project-patcher/issues
Requires-Python: >=3.7
License-File: LICENSE
Requires-Dist: requests (>=2.28)
Requires-Dist: click (>=8.1)
Provides-Extra: all
Requires-Dist: project-patcher[git] ; extra == 'all'
Provides-Extra: git
Requires-Dist: GitPython (>=3.1) ; extra == 'git'
